{
  "subject": "english",
  "stage": "preparatory",
  "grade": "iv",
  "chapter_number": 8,
  "chapter_title": "The Lagori Champions (The Lagori Champions)",
  "main_sections": [
    {
      "section_id": "A",
      "title": "The Lagori Champions",
      "type": "dialogue",
      "page_range": "73–88",
      "page_count": 16,
      "prose_summary": "Chapter 8 is a lively dialogue-and-narration story set in Sundarpur village. Ravi and his cousin Prakash from Rajasthan go to the children's park, where they meet Guneet, Deepa, Nidhi, and Imran. Guneet proposes including Prakash in the upcoming Lagori match because he is a fast runner. Prakash admits he has never heard of Lagori, so Imran explains the rules: seven flat stones are stacked in the centre, one team knocks them down with a ball, and the opposing team tries to rebuild the stack while the first team pelts players with the ball. Prakash recognises the game as 'Satoliya', its name in Rajasthan, which delights the group — they discover the same game has different regional names. Their team is called the Sundarpur Tigers, captained by Deepa, and their opponents are the Green Warriors from a nearby village. In Part II, the match unfolds with high drama: Deepa scores the first hit, the Tigers scramble to rebuild the stack while dodging the ball, and Prakash places the winning seventh stone just before the final whistle. The Tigers win. Both teams shake hands, the referee lifts the captains' hands, and the villagers celebrate together. The story closes with Deepa reflecting that traditional outdoor games are more exciting than video games, and Ravi affirming they should play them more often. Themes: teamwork, sportsmanship, cultural diversity, and the value of traditional games.",
      "spines": {
        "reading": {
          "section_name": "Let us Read + Let us Think A + Let us Think B + Let us Think C + Let us Think D + Let us Think E",
          "tasks_verbatim": [
            {
              "task_text": "Let us Read: Read the dialogue-narrative story 'The Lagori Champions' (pp. 73–79). New Words: match, stacked, opponent, boundary, referee, dodged, teamwork, warriors, cousin.",
              "question_bank": []
            },
            {
              "task_text": "On the basis of your understanding of the text (Part I), answer the following.\n1. Who joined the group in the end?\n2. How many and what kind of stones are used in this game?\n3. In which state of India is the game of Lagori also known as Satoliya?\n4. What is the name of the opponent team of Sundarpur Tigers?",
              "question_bank": [
                {
                  "stem": "Who joined the group in the end?",
                  "type": "SCR",
                  "page_ref": "p.76"
                },
                {
                  "stem": "How many and what kind of stones are used in this game?",
                  "type": "SCR",
                  "page_ref": "p.76"
                },
                {
                  "stem": "In which state of India is the game of Lagori also known as Satoliya?",
                  "type": "SCR",
                  "page_ref": "p.76"
                },
                {
                  "stem": "What is the name of the opponent team of Sundarpur Tigers?",
                  "type": "SCR",
                  "page_ref": "p.76"
                }
              ]
            },
            {
              "task_text": "On the basis of your understanding of the text (Part II), answer the following.\n1. Who blew the whistle to start the match?\n2. Who took the first shot?\n3. What did Prakash do before the final whistle?\n4. Who shook hands at the end of the match? Why?",
              "question_bank": [
                {
                  "stem": "Who blew the whistle to start the match?",
                  "type": "SCR",
                  "page_ref": "p.79"
                },
                {
                  "stem": "Who took the first shot?",
                  "type": "SCR",
                  "page_ref": "p.79"
                },
                {
                  "stem": "What did Prakash do before the final whistle?",
                  "type": "SCR",
                  "page_ref": "p.79"
                },
                {
                  "stem": "Who shook hands at the end of the match? Why?",
                  "type": "SCR",
                  "page_ref": "p.79"
                }
              ]
            },
            {
              "task_text": "Let us Think A. Answer the following.\n1. What is Lagori, and how is it played?\n2. What is the name of Deepa's team, and who are they competing against?\n3. Why is Prakash selected by the captain for playing the Lagori match?\n4. Who told Prakash about Lagori, and what name does he use for it?\n5. What did the villagers do after the Sundarpur Tigers won the match?",
              "question_bank": [
                {
                  "stem": "What is Lagori, and how is it played?",
                  "type": "SCR",
                  "page_ref": "p.80"
                },
                {
                  "stem": "What is the name of Deepa's team, and who are they competing against?",
                  "type": "SCR",
                  "page_ref": "p.80"
                },
                {
                  "stem": "Why is Prakash selected by the captain for playing the Lagori match?",
                  "type": "SCR",
                  "page_ref": "p.80"
                },
                {
                  "stem": "Who told Prakash about Lagori, and what name does he use for it?",
                  "type": "SCR",
                  "page_ref": "p.80"
                },
                {
                  "stem": "What did the villagers do after the Sundarpur Tigers won the match?",
                  "type": "SCR",
                  "page_ref": "p.80"
                }
              ]
            },
            {
              "task_text": "Let us Think C. True or False.\n1. Satoliya is played in Sundarpur village.\n2. Ravi plays for Green Warriors team.\n3. Prakash set the seventh stone on top.\n4. Imran helped Nidhi to dodge the ball.\n5. The Sundarpur Tigers won the match.",
              "question_bank": [
                {
                  "stem": "Satoliya is played in Sundarpur village.",
                  "type": "TRUE_FALSE",
                  "page_ref": "p.81"
                },
                {
                  "stem": "Ravi plays for Green Warriors team.",
                  "type": "TRUE_FALSE",
                  "page_ref": "p.81"
                },
                {
                  "stem": "Prakash set the seventh stone on top.",
                  "type": "TRUE_FALSE",
                  "page_ref": "p.81"
                },
                {
                  "stem": "Imran helped Nidhi to dodge the ball.",
                  "type": "TRUE_FALSE",
                  "page_ref": "p.81"
                },
                {
                  "stem": "The Sundarpur Tigers won the match.",
                  "type": "TRUE_FALSE",
                  "page_ref": "p.81"
                }
              ]
            },
            {
              "task_text": "Let us Think D. Fill in the blanks.\n1. Ravi came ........................ with ........................ dripping down his face.\n2. ........................ is the captain of Sundarpur Tigers.\n3. The Lagori match reminded everyone of the simple joys of ........................ and ........................ .",
              "question_bank": [
                {
                  "stem": "Ravi came ........................ with ........................ dripping down his face.",
                  "type": "FILL_IN",
                  "page_ref": "p.81"
                },
                {
                  "stem": "........................ is the captain of Sundarpur Tigers.",
                  "type": "FILL_IN",
                  "page_ref": "p.81"
                },
                {
                  "stem": "The Lagori match reminded everyone of the simple joys of ........................ and ........................ .",
                  "type": "FILL_IN",
                  "page_ref": "p.81"
                }
              ]
            },
            {
              "task_text": "Let us Think E. Number the sentences in order as per the events given in the story.\n1. The Sundarpur villagers lifted the hands of both the captains and everyone celebrated.\n2. The Green Warriors took the ball and aimed to hit the Tigers.\n3. Nidhi threw the ball with precision, and the stones scattered.\n4. Cheers erupted from the Tigers' side.\n5. All the players from both the team shook hands and appreciated each other for a good game.\n6. The referee blew the whistle and Nidhi took the first shot.\n7. The Sundarpur Tigers began to rebuild the stack of stones.",
              "question_bank": [
                {
                  "stem": "Number the sentences in order as per the events given in the story (7 sentences to sequence).",
                  "type": "MATCH",
                  "page_ref": "p.81"
                }
              ]
            }
          ]
        },
        "oracy": {
          "section_name": "Let us Think B + Let us Listen + Let us Speak A + Let us Speak B",
          "tasks_verbatim": [
            {
              "task_text": "Let us Think B. Think and discuss.\n1. The Sundarpur villagers clapped for both the teams and the referee lifted the hands of both captains. Why did they do so? Do you agree with them?\n2. How does teamwork help in winning games?\n3. According to Deepa, Lagori was more exciting than video games. Do you think she is right? Why or why not?",
              "question_bank": [
                {
                  "stem": "The Sundarpur villagers clapped for both the teams and the referee lifted the hands of both captains. Why did they do so? Do you agree with them?",
                  "type": "ORAL_PROMPT",
                  "page_ref": "p.80"
                },
                {
                  "stem": "How does teamwork help in winning games?",
                  "type": "ORAL_PROMPT",
                  "page_ref": "p.80"
                },
                {
                  "stem": "According to Deepa, Lagori was more exciting than video games. Do you think she is right? Why or why not?",
                  "type": "ORAL_PROMPT",
                  "page_ref": "p.80"
                }
              ]
            },
            {
              "task_text": "Let us Listen: Your teacher will read out short sentences for you. Each sentence has one word in it which is different from the rest. Write down the word that does not fit in each sentence.\n1. I'm learning the rules of different sports like football, basketball, reading, running and swimming.\n2. After school in the playground, we play Gilli Danda, hide and seek, Satoliya, swimming, hopscotch, skipping and hockey.\n3. My brother likes to play Kabbadi, basketball, badminton, kho-kho, knitting and Lagori.\n4. In the sports class, we get training for climbing, sprinting, jumping, stretching and writing.\n5. We use a ball while playing cricket, hockey, skipping, tennis and volleyball.",
              "question_bank": [
                {
                  "stem": "Identify the word that does not fit: 'I'm learning the rules of different sports like football, basketball, reading, running and swimming.'",
                  "type": "ORAL_PROMPT",
                  "page_ref": "p.84"
                },
                {
                  "stem": "Identify the word that does not fit: 'After school in the playground, we play Gilli Danda, hide and seek, Satoliya, swimming, hopscotch, skipping and hockey.'",
                  "type": "ORAL_PROMPT",
                  "page_ref": "p.84"
                },
                {
                  "stem": "Identify the word that does not fit: 'My brother likes to play Kabbadi, basketball, badminton, kho-kho, knitting and Lagori.'",
                  "type": "ORAL_PROMPT",
                  "page_ref": "p.84"
                },
                {
                  "stem": "Identify the word that does not fit: 'In the sports class, we get training for climbing, sprinting, jumping, stretching and writing.'",
                  "type": "ORAL_PROMPT",
                  "page_ref": "p.84"
                },
                {
                  "stem": "Identify the word that does not fit: 'We use a ball while playing cricket, hockey, skipping, tennis and volleyball.'",
                  "type": "ORAL_PROMPT",
                  "page_ref": "p.84"
                }
              ],
              "transcript_ref": "p.84",
              "transcript_text": "1. I'm learning the rules of different sports like football, basketball, reading, running and swimming. 2. After school in the playground, we play Gilli Danda, hide and seek, Satoliya, swimming, hopscotch, skipping and hockey. 3. My brother likes to play Kabbadi, basketball, badminton, kho-kho, knitting and Lagori. 4. In the sports class, we get training for climbing, sprinting, jumping, stretching and writing. 5. We use a ball while playing cricket, hockey, skipping, tennis and volleyball."
            },
            {
              "task_text": "Let us Speak A: Speak to your playmates and find out who enjoys outdoor games, enjoys riding a bicycle, likes art, loves to do gardening, loves to eat pomegranate, likes to eat vegetables, is born in December, favourite colour is Grey, favourite candy is chocolate, has visited a sports stadium, does yoga everyday, likes to read, is an only child, likes to play games, is a good swimmer, has a bat or ball, first name starts with an 'M', has a badminton racquet, who loves to play Lagori or Satoliya, has seen India Gate.",
              "question_bank": [
                {
                  "stem": "Find a classmate who enjoys outdoor games.",
                  "type": "ORAL_PROMPT",
                  "page_ref": "p.84"
                },
                {
                  "stem": "Find a classmate who enjoys riding a bicycle.",
                  "type": "ORAL_PROMPT",
                  "page_ref": "p.84"
                },
                {
                  "stem": "Find a classmate who likes art.",
                  "type": "ORAL_PROMPT",
                  "page_ref": "p.84"
                },
                {
                  "stem": "Find a classmate who loves to do gardening.",
                  "type": "ORAL_PROMPT",
                  "page_ref": "p.84"
                },
                {
                  "stem": "Find a classmate who loves to play Lagori or Satoliya.",
                  "type": "ORAL_PROMPT",
                  "page_ref": "p.85"
                }
              ]
            },
            {
              "task_text": "Let us Speak B: Talk about any one community game or match organised in your village/locality/colony. Have you participated in it?",
              "question_bank": [
                {
                  "stem": "Talk about any one community game or match organised in your village/locality/colony. Have you participated in it?",
                  "type": "ORAL_PROMPT",
                  "page_ref": "p.85"
                }
              ]
            }
          ]
        },
        "word_work": {
          "section_name": "Let us Learn A + Let us Learn B",
          "tasks_verbatim": [
            {
              "task_text": "Let us Learn A: Circle the word that does not have the same meaning as the word in bold.\n1. Together, the students built a large sand castle during recess. [huge / tiny / big]\n2. The whole school praised the victory of the basketball team. [celebrated / ignored / cheered]\n3. Diksha coloured the margin of the page. [boundary / border / center]\n4. Today there was an exciting football contest at school. [match / playground / activity]\n5. The loud noise caused a jolt to everyone in the room. [shock / calm / disturbance]\n6. The parents worked together to repair the playground for the children. [rebuild / mend / ruin]\n7. Her most-liked subject in school is art. [favourite / beloved / disliked]\n8. Her rival in the game was her best friend. [opponent / competitor / friend]",
              "question_bank": [
                {
                  "stem": "Circle the word that does NOT mean the same as 'large': huge / tiny / big",
                  "type": "MCQ",
                  "options": [
                    "huge",
                    "tiny",
                    "big"
                  ],
                  "page_ref": "p.82"
                },
                {
                  "stem": "Circle the word that does NOT mean the same as 'praised': celebrated / ignored / cheered",
                  "type": "MCQ",
                  "options": [
                    "celebrated",
                    "ignored",
                    "cheered"
                  ],
                  "page_ref": "p.82"
                },
                {
                  "stem": "Circle the word that does NOT mean the same as 'margin': boundary / border / center",
                  "type": "MCQ",
                  "options": [
                    "boundary",
                    "border",
                    "center"
                  ],
                  "page_ref": "p.82"
                },
                {
                  "stem": "Circle the word that does NOT mean the same as 'contest': match / playground / activity",
                  "type": "MCQ",
                  "options": [
                    "match",
                    "playground",
                    "activity"
                  ],
                  "page_ref": "p.82"
                },
                {
                  "stem": "Circle the word that does NOT mean the same as 'jolt': shock / calm / disturbance",
                  "type": "MCQ",
                  "options": [
                    "shock",
                    "calm",
                    "disturbance"
                  ],
                  "page_ref": "p.82"
                },
                {
                  "stem": "Circle the word that does NOT mean the same as 'repair': rebuild / mend / ruin",
                  "type": "MCQ",
                  "options": [
                    "rebuild",
                    "mend",
                    "ruin"
                  ],
                  "page_ref": "p.82"
                },
                {
                  "stem": "Circle the word that does NOT mean the same as 'most-liked': favourite / beloved / disliked",
                  "type": "MCQ",
                  "options": [
                    "favourite",
                    "beloved",
                    "disliked"
                  ],
                  "page_ref": "p.83"
                },
                {
                  "stem": "Circle the word that does NOT mean the same as 'rival': opponent / competitor / friend",
                  "type": "MCQ",
                  "options": [
                    "opponent",
                    "competitor",
                    "friend"
                  ],
                  "page_ref": "p.83"
                }
              ]
            },
            {
              "task_text": "Let us Learn B: Let's unscramble the letters as per the meaning of the words given.\n1. Hint: 'a place or region beyond a boundary' — D E O T I U S\n2. Hint: 'to raise your hand and move it from side to side as a way of greeting someone' — V E A W\n3. Hint: 'a sports competition or event in which two people or two teams compete against each other' — H M T A C\n4. Hint: 'a child of a person's aunt or uncle' — I O U N S C",
              "question_bank": [
                {
                  "stem": "Unscramble: D E O T I U S — Hint: 'a place or region beyond a boundary'",
                  "type": "FILL_IN",
                  "page_ref": "p.83"
                },
                {
                  "stem": "Unscramble: V E A W — Hint: 'to raise your hand and move it from side to side as a way of greeting someone'",
                  "type": "FILL_IN",
                  "page_ref": "p.83"
                },
                {
                  "stem": "Unscramble: H M T A C — Hint: 'a sports competition or event in which two people or two teams compete against each other'",
                  "type": "FILL_IN",
                  "page_ref": "p.83"
                },
                {
                  "stem": "Unscramble: I O U N S C — Hint: 'a child of a person's aunt or uncle'",
                  "type": "FILL_IN",
                  "page_ref": "p.83"
                }
              ]
            }
          ]
        },
        "writing": {
          "section_name": "Let us Write A + Let us Write B + Let us Write C",
          "tasks_verbatim": [
            {
              "task_text": "Let us Write A: Word Treasure Hunt. Some words from the story are hidden in the word grid below. One word has been done for you (SWEAT). Find at least six words in the box. Use these words in sentences of your own.",
              "question_bank": [
                {
                  "stem": "Find at least six story words hidden in the word-search grid (one example given: SWEAT). Use each found word in a sentence of your own.",
                  "type": "WRITING_TASK",
                  "page_ref": "p.85"
                }
              ],
              "visual_stimulus": [
                {
                  "type": "grid",
                  "count": 1,
                  "brief_description": "10×10 word-search grid containing hidden words from the story (e.g. SWEAT, INCLUDE, STACKED, DODGED, WINNER, REFEREE, etc.)",
                  "page_ref": "p.85"
                }
              ]
            },
            {
              "task_text": "Let us Write B: Rearrange the words to form meaningful sentences.\n1. boundary / field / is / the / marked / a / with\n2. looked / prakash / at / surprise / everybody / with\n3. peacock / saw / a / dancing / I / the / in / rain\n4. white / there / and / grey / are / the / clouds / sky / in\n5. fresh / need / every day / water / plants",
              "question_bank": [
                {
                  "stem": "Rearrange: boundary / field / is / the / marked / a / with",
                  "type": "FILL_IN",
                  "page_ref": "p.86"
                },
                {
                  "stem": "Rearrange: looked / prakash / at / surprise / everybody / with",
                  "type": "FILL_IN",
                  "page_ref": "p.86"
                },
                {
                  "stem": "Rearrange: peacock / saw / a / dancing / I / the / in / rain",
                  "type": "FILL_IN",
                  "page_ref": "p.86"
                },
                {
                  "stem": "Rearrange: white / there / and / grey / are / the / clouds / sky / in",
                  "type": "FILL_IN",
                  "page_ref": "p.86"
                },
                {
                  "stem": "Rearrange: fresh / need / every day / water / plants",
                  "type": "FILL_IN",
                  "page_ref": "p.86"
                }
              ]
            },
            {
              "task_text": "Let us Write C: Tick the right box — Sentence or Question.\n1. My name is Sonam.\n2. What is your name?\n3. Where do you stay?\n4. This flower is beautiful.\n5. My shirt is blue in colour.",
              "question_bank": [
                {
                  "stem": "My name is Sonam. — Sentence or Question?",
                  "type": "MCQ",
                  "options": [
                    "Sentence",
                    "Question"
                  ],
                  "page_ref": "p.87"
                },
                {
                  "stem": "What is your name? — Sentence or Question?",
                  "type": "MCQ",
                  "options": [
                    "Sentence",
                    "Question"
                  ],
                  "page_ref": "p.87"
                },
                {
                  "stem": "Where do you stay? — Sentence or Question?",
                  "type": "MCQ",
                  "options": [
                    "Sentence",
                    "Question"
                  ],
                  "page_ref": "p.87"
                },
                {
                  "stem": "This flower is beautiful. — Sentence or Question?",
                  "type": "MCQ",
                  "options": [
                    "Sentence",
                    "Question"
                  ],
                  "page_ref": "p.87"
                },
                {
                  "stem": "My shirt is blue in colour. — Sentence or Question?",
                  "type": "MCQ",
                  "options": [
                    "Sentence",
                    "Question"
                  ],
                  "page_ref": "p.87"
                }
              ]
            }
          ]
        },
        "beyond_text": {
          "section_name": "Let us Do A + Let us Do B",
          "tasks_verbatim": [
            {
              "task_text": "Let us Do A: Divide the class into small groups and imagine that you are forming a Lagori team. Each team will create your own 'Lagori Team Badge' using art and creativity, reflecting your understanding of teamwork and traditional games. Materials: drawing sheets, coloured pencils, markers, glitter, and other decorative materials. Each group decides a team name (e.g., Rainbow Runners or Sky Warriors) and designs a unique badge or logo representing their team's spirit, values, or region (can include stacked stones, a ball, or symbols of unity and tradition). Each group presents their badge to the class and explains the meaning behind their design and how it reflects the spirit of Lagori and teamwork.",
              "question_bank": [
                {
                  "stem": "Design a 'Lagori Team Badge' in your group. Decide a team name, create the badge, then present it to the class explaining the meaning of your design and how it reflects Lagori and teamwork.",
                  "type": "PROJECT",
                  "page_ref": "p.87"
                }
              ]
            },
            {
              "task_text": "Let us Do B: Point out the eight differences between the two pictures given below.",
              "question_bank": [
                {
                  "stem": "Find and point out the eight differences between the two pictures.",
                  "type": "ORAL_PROMPT",
                  "page_ref": "p.88"
                }
              ],
              "visual_stimulus": [
                {
                  "type": "picture",
                  "count": 2,
                  "brief_description": "Two near-identical scenes of a Lagori/outdoor game match with eight subtle differences to spot (e.g. missing bird, different balloon colour, number of flowers, etc.)",
                  "page_ref": "p.88"
                }
              ]
            }
          ]
        }
      }
    }
  ],
  "competency_reporting": {
    "by_spine": {
      "oracy": [
        "C-1.1",
        "C-1.2",
        "C-1.3"
      ],
      "reading": [
        "C-2.1",
        "C-2.2"
      ],
      "writing": [
        "C-3.1",
        "C-3.2",
        "C-3.3",
        "C-3.4"
      ],
      "word_work": [
        "C-4.1",
        "C-4.2"
      ],
      "beyond_text": [
        "C-5.1",
        "C-5.2"
      ]
    }
  },
  "effort_signals": {
    "spine_load": 3.0,
    "task_density": 2.0,
    "writing_demand": 2.0,
    "project_load": 1.0,
    "effort_index": 13.0
  },
  "_source_unit": {
    "unit_chapter_number": 8,
    "unit_chapter_title": "The Lagori Champions",
    "section_id": "A",
    "page_count": 16,
    "page_share_of_unit": 1.0
  }
}